Dockerfile
LICENSE
MANIFEST.in
Makefile
README.rst
VERSION
classifiers.txt
requirements.txt
setup.py
cn_hyperarr/__init__.py
cn_hyperarr/database.py
cn_hyperarr/infinite_families.py
cn_hyperarr/main.py
cn_hyperarr/vector_classes.py
cn_hyperarr.egg-info/PKG-INFO
cn_hyperarr.egg-info/SOURCES.txt
cn_hyperarr.egg-info/dependency_links.txt
cn_hyperarr.egg-info/requires.txt
cn_hyperarr.egg-info/top_level.txt
docs/Makefile
docs/build/html/computations.html
docs/build/html/database.html
docs/build/html/genindex.html
docs/build/html/index.html
docs/build/html/inf_fam.html
docs/build/html/installation.html
docs/build/html/objects.inv
docs/build/html/py-modindex.html
docs/build/html/search.html
docs/build/html/searchindex.js
docs/build/html/vector_conf.html
docs/build/html/_static/MathJax.js
docs/build/html/_static/basic.css
docs/build/html/_static/classic.css
docs/build/html/_static/default.css
docs/build/html/_static/doctools.js
docs/build/html/_static/documentation_options.js
docs/build/html/_static/file.png
docs/build/html/_static/jquery-3.5.1.js
docs/build/html/_static/jquery.js
docs/build/html/_static/language_data.js
docs/build/html/_static/latest.js
docs/build/html/_static/minus.png
docs/build/html/_static/plus.png
docs/build/html/_static/pygments.css
docs/build/html/_static/searchtools.js
docs/build/html/_static/sidebar.js
docs/build/html/_static/underscore-1.3.1.js
docs/build/html/_static/underscore.js
docs/build/html/_static/config/AM_CHTML-full.js
docs/build/html/_static/config/AM_CHTML.js
docs/build/html/_static/config/AM_HTMLorMML-full.js
docs/build/html/_static/config/AM_HTMLorMML.js
docs/build/html/_static/config/AM_SVG-full.js
docs/build/html/_static/config/AM_SVG.js
docs/build/html/_static/config/Accessible-full.js
docs/build/html/_static/config/Accessible.js
docs/build/html/_static/config/MML_CHTML-full.js
docs/build/html/_static/config/MML_CHTML.js
docs/build/html/_static/config/MML_HTMLorMML-full.js
docs/build/html/_static/config/MML_HTMLorMML.js
docs/build/html/_static/config/MML_SVG-full.js
docs/build/html/_static/config/MML_SVG.js
docs/build/html/_static/config/MMLorHTML.js
docs/build/html/_static/config/Safe.js
