Metadata-Version: 1.1
Name: cn_hyperarr
Version: 0.0.1
Summary: Computation of congruence normality for hyperplane arrangements
Home-page: https://github.com/sophiasage/cn_hyperarr
Author: Sophia Elia
Author-email: sophiae56@zedat.fu-berlin.de
License: GNU General Public License v3
Keywords: SageMath packaging
Platform: UNKNOWN
Classifier: 
Classifier: Development Status :: 4 - Beta
Classifier: Intended Audience :: Science/Research
Classifier: Topic :: Scientific/Engineering :: Mathematics
Classifier: License :: OSI Approved :: GNU General Public License v3 (GPLv3)
Classifier: Programming Language :: Python :: 3.1
Classifier: 
